refcount/__init__.py
pyrefcount-0.1.0.dist-info/LICENSE
pyrefcount-0.1.0.dist-info/METADATA
pyrefcount-0.1.0.dist-info/WHEEL
pyrefcount-0.1.0.dist-info/top_level.txt
pyrefcount-0.1.0.dist-info/RECORD
