Metadata-Version: 2.1
Name: pyrefcount
Version: 0.1.0
Summary: UNKNOWN
Home-page: https://github.com/pmundt/pyrefcount
Author: Paul Mundt
Author-email: paul.mundt@adaptant.io
License: MIT
Keywords: refcount
Platform: UNKNOWN
Classifier: Development Status :: 4 - Beta
Classifier: Intended Audience :: Developers
Classifier: Programming Language :: Python :: 2
Classifier: Programming Language :: Python :: 3
Classifier: License :: OSI Approved :: MIT License
Classifier: Topic :: Software Development :: Libraries
Classifier: Topic :: Software Development :: Libraries :: Python Modules
Classifier: Topic :: Software Development :: Object Brokering
